Metadata-Version: 1.0
Name: feature-classify
Version: 0.2
Summary: feature classify
Home-page: UNKNOWN
Author: bodong
Author-email: dongbocool@163.com
License: UNKNOWN
Platform: UNKNOWN
